<annotation>
	<folder>cropped</folder>
	<filename>IMG_8564.jpg</filename>
	<path>/Users/zach/Desktop/SDP/dartboard-cv-score-system/data/cropped/IMG_8564.jpg</path>
	<source>
		<database>Unknown</database>
	</source>
	<size>
		<width>800</width>
		<height>800</height>
		<depth>3</depth>
	</size>
	<segmented>0</segmented>
	<object>
		<name>twenty</name>
		<pose>Unspecified</pose>
		<truncated>0</truncated>
		<difficult>0</difficult>
		<bndbox>
			<xmin>301</xmin>
			<ymin>43</ymin>
			<xmax>366</xmax>
			<ymax>101</ymax>
		</bndbox>
	</object>
	<object>
		<name>six</name>
		<pose>Unspecified</pose>
		<truncated>0</truncated>
		<difficult>0</difficult>
		<bndbox>
			<xmin>741</xmin>
			<ymin>397</ymin>
			<xmax>791</xmax>
			<ymax>425</ymax>
		</bndbox>
	</object>
	<object>
		<name>three</name>
		<pose>Unspecified</pose>
		<truncated>0</truncated>
		<difficult>0</difficult>
		<bndbox>
			<xmin>417</xmin>
			<ymin>745</ymin>
			<xmax>445</xmax>
			<ymax>785</ymax>
		</bndbox>
	</object>
	<object>
		<name>eleven</name>
		<pose>Unspecified</pose>
		<truncated>0</truncated>
		<difficult>0</difficult>
		<bndbox>
			<xmin>3</xmin>
			<ymin>480</ymin>
			<xmax>55</xmax>
			<ymax>527</ymax>
		</bndbox>
	</object>
	<object>
		<name>dart</name>
		<pose>Unspecified</pose>
		<truncated>0</truncated>
		<difficult>0</difficult>
		<bndbox>
			<xmin>214</xmin>
			<ymin>366</ymin>
			<xmax>236</xmax>
			<ymax>392</ymax>
		</bndbox>
	</object>
	<object>
		<name>dart</name>
		<pose>Unspecified</pose>
		<truncated>0</truncated>
		<difficult>0</difficult>
		<bndbox>
			<xmin>502</xmin>
			<ymin>685</ymin>
			<xmax>522</xmax>
			<ymax>712</ymax>
		</bndbox>
	</object>
</annotation>
